setup.cfg
setup.py
ntlm3/HTTPNtlmAuthHandler.py
ntlm3/U32.py
ntlm3/__init__.py
ntlm3/compat.py
ntlm3/des.py
ntlm3/des_c.py
ntlm3/des_data.py
ntlm3/ntlm.py
ntlm3/smtp.py
shadiakiki1986_python_ntlm3.egg-info/PKG-INFO
shadiakiki1986_python_ntlm3.egg-info/SOURCES.txt
shadiakiki1986_python_ntlm3.egg-info/dependency_links.txt
shadiakiki1986_python_ntlm3.egg-info/not-zip-safe
shadiakiki1986_python_ntlm3.egg-info/requires.txt
shadiakiki1986_python_ntlm3.egg-info/top_level.txt